backward/__init__.py
backward/__main__.py
backward/backward.py
backward/evaluate.py
backward/read.py
backward-0.0.4.dist-info/LICENSE
backward-0.0.4.dist-info/METADATA
backward-0.0.4.dist-info/WHEEL
backward-0.0.4.dist-info/entry_points.txt
backward-0.0.4.dist-info/top_level.txt
backward-0.0.4.dist-info/zip-safe
backward-0.0.4.dist-info/RECORD
