Metadata-Version: 2.1
Name: backward
Version: 0.0.4
Summary: A simple programming language and inference engine powered by backward chaining.
Home-page: https://github.com/gidona18/backward
Author: Armando Herrera
Author-email: gidona18@estegio.com
License: Apache-2.0
Platform: UNKNOWN
Classifier: License :: OSI Approved :: Apache Software License
Classifier: Programming Language :: Python :: 3
Classifier: Programming Language :: Python :: 3.0
Classifier: Programming Language :: Python :: 3.1
Classifier: Programming Language :: Python :: 3.2
Classifier: Programming Language :: Python :: 3.3
Classifier: Programming Language :: Python :: 3.4
Classifier: Programming Language :: Python :: 3.5
Classifier: Programming Language :: Python :: 3.6
Classifier: Programming Language :: Python :: 3.7
Classifier: Programming Language :: Python :: 3.8
Requires-Dist: lark-parser
Requires-Dist: protoclass
